aioxdl/__init__.py
aioxdl/exception/__init__.py
aioxdl/exception/exceptions.py
aioxdl/functions/__init__.py
aioxdl/functions/collections.py
aioxdl/functions/function01.py
aioxdl/functions/function02.py
aioxdl/functions/function03.py
aioxdl/modules/__init__.py
aioxdl/modules/module01.py
aioxdl/modules/module02.py
aioxdl/scripts/__init__.py
aioxdl/scripts/en.py
aioxdl-0.0.31.dist-info/METADATA
aioxdl-0.0.31.dist-info/WHEEL
aioxdl-0.0.31.dist-info/top_level.txt
aioxdl-0.0.31.dist-info/RECORD
